syntrac_opentelemetry/instrumentation/openai/__init__.py
syntrac_opentelemetry/instrumentation/openai/shared/__init__.py
syntrac_opentelemetry/instrumentation/openai/shared/chat_wrappers.py
syntrac_opentelemetry/instrumentation/openai/shared/completion_wrappers.py
syntrac_opentelemetry/instrumentation/openai/shared/config.py
syntrac_opentelemetry/instrumentation/openai/shared/embeddings_wrappers.py
syntrac_opentelemetry/instrumentation/openai/shared/image_gen_wrappers.py
syntrac_opentelemetry/instrumentation/openai/utils.py
syntrac_opentelemetry/instrumentation/openai/v0/__init__.py
syntrac_opentelemetry/instrumentation/openai/v1/__init__.py
syntrac_opentelemetry/instrumentation/openai/v1/assistant_wrappers.py
syntrac_opentelemetry/instrumentation/openai/v1/event_handler_wrapper.py
syntrac_opentelemetry/instrumentation/openai/version.py
syntrac_opentelemetry_instrumentation_openai-0.0.2.dist-info/METADATA
syntrac_opentelemetry_instrumentation_openai-0.0.2.dist-info/WHEEL
syntrac_opentelemetry_instrumentation_openai-0.0.2.dist-info/entry_points.txt
syntrac_opentelemetry_instrumentation_openai-0.0.2.dist-info/RECORD
